tty2img.py
tty2img-0.3.6.dist-info/LICENSE
tty2img-0.3.6.dist-info/METADATA
tty2img-0.3.6.dist-info/WHEEL
tty2img-0.3.6.dist-info/top_level.txt
tty2img-0.3.6.dist-info/RECORD
